{
    "details": {
        "title": "ब्रह्मतत्त्वप्रकाशिका नाम ब्रह्मसूत्रवृत्तिः",
        "contributors": {
            "author": [
                "श्रीसदाशिवेन्द्रसरस्वत्या",
                "गणपतिशास्त्रिणा"
            ]
        },
        "attributes": {
            "edition": "1",
            "year": ""
        },
        "collection": [
            {
                "name": "Trivandrum Sanskrit Series - Anantasayana Samskrita Granthavali",
                "index": "7"
            }
        ]
    },
    "media": {
        "pdf": {
            "link": "https://ia601602.us.archive.org/20/items/Trivandrum_Sanskrit_Series_TSS/TSS-007_Brahmatatwa_Prakasika_of_Sadasivendra_Saraswati_-_T_Ganapati_Sastri_1909.pdf"
        }
    }
}