{
    "details": {
        "bookId": "book_00348",
        "title": "अध्वरमीमांसा कुतूहलवृत्तिः",
        "contributors": {
            "author": [
                "वासुदेवदीक्षित"
            ]
        },
        "attributes": {
            "edition": "1",
            "year": ""
        },
        "collection": [
            {
                "category": "Shastra",
                "veda": "",
                "name": "",
                "index": "0"
            }
        ]
    },
    "media": {
        "pdf": {
            "link": "https://ia800203.us.archive.org/3/items/adhvaramimamsaku01vasu/adhvaramimamsaku01vasu.pdf"
        }
    }
}