{
    "details": {
        "title": "",
        "contributors": {
            "author": [
                ""
            ]
        },
        "attributes": {
            "edition": "1",
            "year": ""
        },
        "collection": [
            {
                "name": "Trivandrum Sanskrit Series - Anantasayana Samskrita Granthavali",
                "index": "40"
            }
        ]
    },
    "media": {
        "pdf": {
            "link": "https://ia601602.us.archive.org/20/items/Trivandrum_Sanskrit_Series_TSS/TSS-040_Alankarasutram_of_Rajanaka_Ruyyaka_-_TG_Sastri_1919.pdf"
        }
    }
}