{
    "details": {
        "title": "महामुनिश्रीमद्व्यासप्रणीतं वायुपुराणम्",
        "contributors": {
            "author": [
                "हरि नारायण आपटे"
            ]
        },
        "attributes": {
            "edition": "1",
            "year": "1905"
        },
        "collection": [
            {
                "category": "Ithihasa Purana",
                "name": "Anandashram Samskrita Granthavali",
                "index": "49"
            }
        ]
    },
    "media": {
        "pdf": {
            "link": "https://ia801704.us.archive.org/2/items/Anandashram_Samskrita_Granthavali_Anandashram_Sanskrit_Series/ASS_049_Vayu_Puranam_-_HN_Apte_1905.pdf"
        }
    }
}